csvdedupe/__init__.py
csvdedupe/csvdedupe.py
csvdedupe/csvhelpers.py
csvdedupe/csvlink.py
csvdedupe2-0.2.7.dist-info/LICENSE.md
csvdedupe2-0.2.7.dist-info/METADATA
csvdedupe2-0.2.7.dist-info/WHEEL
csvdedupe2-0.2.7.dist-info/entry_points.txt
csvdedupe2-0.2.7.dist-info/top_level.txt
csvdedupe2-0.2.7.dist-info/RECORD
