Metadata-Version: 2.1
Name: csvdedupe2
Version: 0.2.7
Summary: Command line tools for deduplicating and merging csv files
Author: Forest Gregg, Derek Eder, Wiktor Strzebała
License: MIT
Platform: UNKNOWN
License-File: LICENSE.md
Requires-Dist: future (>=0.14)
Requires-Dist: dedupe (<2,>=1.6)
